erddapClient/__init__.py
erddapClient/erddap_constants.py
erddapClient/erddap_dataset.py
erddapClient/erddap_griddap.py
erddapClient/erddap_griddap_dimensions.py
erddapClient/erddap_server.py
erddapClient/erddap_tabledap.py
erddapClient/formatting.py
erddapClient/parse_utils.py
erddapClient/pyerddap.py
erddapClient/remote_requests.py
erddapClient/url_operations.py
erddap_python-1.0.0.dist-info/LICENSE.txt
erddap_python-1.0.0.dist-info/METADATA
erddap_python-1.0.0.dist-info/WHEEL
erddap_python-1.0.0.dist-info/top_level.txt
erddap_python-1.0.0.dist-info/RECORD
