Metadata-Version: 2.1
Name: erddap-python
Version: 1.0.0
Summary: Python erddap API client
Home-page: https://github.com/hmedrano/erddap-python
Author: Favio Medrano
Author-email: hmedrano@cicese.mx
License: MIT
Platform: UNKNOWN
Classifier: Programming Language :: Python :: 3
Classifier: License :: OSI Approved :: MIT License
Classifier: Operating System :: OS Independent
Requires-Python: >=3.6
Requires-Dist: pandas
Requires-Dist: requests
Requires-Dist: xarray
Requires-Dist: netCDF4
